Workbook

Sheet README
A1: IntelIntent Investment Dashboard — Quick Start
A3: How to use:
A4: 1) Enter/append your real transactions in the Transactions sheet.
A5: 2) Update Holdings with your actual symbols, quantities, and cost basis.
A6: 3) Paste price history in Prices (Date, Symbol, Close) — one row per date & symbol.
A7: (For quick use, keep the sample data; the Dashboard will update automatically.)
A8: 4) Adjust Settings to your situation (monthly expenses, safe withdrawal rate).
A9: 5) View Dashboard for allocation, trend, cashflow, and retirement readiness.
A11: Notes:
A12: - Latest prices are pulled per symbol using a LOOKUP to the last available row.
A13: - Portfolio History uses sample data for a 60-day trend. Replace with your data as needed.
A14: - This workbook is Power BI–ready: you can connect Power BI to the Transactions, Holdings, and Prices tables.

Sheet Settings
A1: Setting | B1: Value
A2: Monthly_Expense_Baseline | B2: 4500
A3: Safe_Withdrawal_Rate_% | B3: 4
A4: Target_Retirement_Income_Monthly | B4: 6000

Sheet Accounts
A1: Account
A2: Checking
A3: Brokerage
A4: IRA
A5: Savings

Sheet Categories
A1: Type | B1: Category
A2: Income | B2: Salary
A3: Income | B3: Other
A4: Expense | B4: Housing
A5: Expense | B5: Utilities
A6: Expense | B6: Food
A7: Expense | B7: Transportation
A8: Expense | B8: Healthcare
A9: Expense | B9: Investment

Sheet Transactions
A1: Date | B1: Account | C1: Type | D1: Category | E1: Subcategory | F1: Description | G1: Amount
A2: 45848 | B2: Checking | C2: Income | D2: Salary | E2: Paycheck | F2: Monthly paycheck | G2: 6000
A3: 45853 | B3: Checking | C3: Expense | D3: Housing | E3: Rent | F3: June rent | G3: -1800
A4: 45855 | B4: Checking | C4: Expense | D4: Utilities | E4: Electric | F4: TXU bill | G4: -210.45
A5: 45863 | B5: Brokerage | C5: Expense | D5: Investment | E5: Buy | F5: Buy FNGU | G5: -3375
A6: 45864 | B6: Brokerage | C6: Expense | D6: Investment | E6: Buy | F6: Buy SPY | G6: -10100
A7: 45878 | B7: Checking | C7: Expense | D7: Food | E7: Groceries | F7: Groceries | G7: -285.72
A8: 45883 | B8: Checking | C8: Income | D8: Other | E8: Refund | F8: Tax refund | G8: 450

Sheet Holdings
A1: Account | B1: Symbol | C1: Quantity | D1: CostBasis | E1: LatestPrice | F1: MarketValue | G1: UnrealizedGain
A2: Brokerage | B2: FNGU | C2: 150 | D2: 3750 | E2: =LOOKUP(2,1/(Prices!$B:$B=Holdings!B2),Prices!$C:$C) | F2: =C2*E2 | G2: =F2-D2
A3: Brokerage | B3: SPY | C3: 20 | D3: 10000 | E3: =LOOKUP(2,1/(Prices!$B:$B=Holdings!B3),Prices!$C:$C) | F3: =C3*E3 | G3: =F3-D3

Sheet Prices
A1: Date | B1: Symbol | C1: Close
A2: 45828 | B2: FNGU | C2: 30.31
A3: 45829 | B3: FNGU | C3: 30.24
A4: 45830 | B4: FNGU | C4: 30.65
A5: 45831 | B5: FNGU | C5: 31.6
A6: 45832 | B6: FNGU | C6: 31.47
A7: 45833 | B7: FNGU | C7: 31.34
A8: 45834 | B8: FNGU | C8: 32.34
A9: 45835 | B9: FNGU | C9: 32.85
A10: 45836 | B10: FNGU | C10: 32.56
A11: 45837 | B11: FNGU | C11: 32.93
A12: 45838 | B12: FNGU | C12: 32.64
A13: 45839 | B13: FNGU | C13: 32.36
... A123: 45888 | B123: SPY | C123: 531.85

Sheet Portfolio_History
A1: Date | B1: TotalValue | C1: FNGU_Value | D1: SPY_Value
A2: 45828 | B2: 14913.1 | C2: 4546.5 | D2: 10366.6
A3: 45829 | B3: 14678.4 | C3: 4536 | D3: 10142.4
A4: 45830 | B4: 14502.3 | C4: 4597.5 | D4: 9904.8
A5: 45831 | B5: 14810.8 | C5: 4740 | D5: 10070.8
A6: 45832 | B6: 15069.5 | C6: 4720.5 | D6: 10349
A7: 45833 | B7: 15040.2 | C7: 4701 | D7: 10339.2
A8: 45834 | B8: 15402.8 | C8: 4851 | D8: 10551.8
A9: 45835 | B9: 15560.9 | C9: 4927.5 | D9: 10633.4
A10: 45836 | B10: 15385.6 | C10: 4884 | D10: 10501.6
A11: 45837 | B11: 15522.3 | C11: 4939.5 | D11: 10582.8
A12: 45838 | B12: 15809.6 | C12: 4896 | D12: 10913.6
A13: 45839 | B13: 15765.2 | C13: 4854 | D13: 10911.2
... A62: 45888 | B62: 14415.5 | C62: 3778.5 | D62: 10637

Sheet Cashflow
A1: YearMonth | B1: Expense | C1: Income | D1: Net
A2: 2025-07 | B2: -15485.45 | C2: 6000 | D2: -9485.45
A3: 2025-08 | B3: -285.72 | C3: 450 | D3: 164.28

Sheet Summary
A1: Metric | B1: Value
A2: Total Portfolio Value | B2: =SUM(Holdings!F2:F3)
A3: Total Cost Basis | B3: =SUM(Holdings!D2:D3)
A4: Total Unrealized Gain | B4: =SUM(Holdings!G2:G3)
A5: Monthly Income (last full month) | B5: =SUMIF(Cashflow!A:A,B13,Cashflow!B:B)
A6: Monthly Expenses (last full month) | B6: =SUMIF(Cashflow!A:A,B13,Cashflow!C:C)
A7: Net Cashflow (last full month) | B7: =SUMIF(Cashflow!A:A,B13,Cashflow!D:D)
A8: Monthly Expense Baseline (Settings) | B8: =Settings!B2
A9: Safe Withdrawal Rate % (Settings) | B9: =Settings!B3
A10: Target Retirement Income Monthly | B10: =Settings!B4
A11: Required Nest Egg (Baseline/SWR) | B11: =(Settings!B2*12)/(Settings!B3/100)
A12: Funded Ratio (Portfolio / Required) | B12: =B2/B10
A13: Last Full Month (YYYY-MM) | B13: =TEXT(EDATE(TODAY(),-1),yyyy-mm)

Sheet Dashboard
A1: IntelIntent Investment Dashboard
A3: Symbol | B3: MarketValue
A4: =Holdings!B2 | B4: =Holdings!F2
A5: =Holdings!B3 | B5: =Holdings!F3
A6: Total Portfolio Value: | B6: =Summary!B2
A7: Unrealized Gain: | B7: =Summary!B4
A8: Funded Ratio: | B8: =Summary!B11
