Workbook

Sheet README
A1: IntelIntent Investment Dashboard — Quick Start (v2)
A3: 1) Go to the Dashboard sheet to see allocation, trend, and cashflow.
A4: 2) Update Settings (Monthly Expense Baseline, SWR, Target Retirement Income).
A5: 3) Enter your holdings in Holdings; paste prices in Prices.
A6: 4) Add income/expenses in Transactions (positive = income, negative = expense).
A7: 5) Summary shows your Required Nest Egg and Funded Ratio.
A8: Tip: Press F11 on Dashboard for full-screen TV mode.

Sheet Dad_OnePager
A1: IntelIntent — Dad’s One Pager
A3: What this is | B3: A living view of cashflow and portfolio readiness.
A5: Look here first | B5: On Dashboard: Portfolio Value, Unrealized Gain, Funded Ratio.
A7: Funded Ratio | B7: At 100%+, the portfolio can cover baseline spending at chosen SWR.
A9: Update cadence | B9: Adjust Settings as life changes; paste transactions monthly; update prices weekly or on demand.

Sheet Settings
A1: Setting | B1: Value
A2: Monthly_Expense_Baseline | B2: 4500
A3: Safe_Withdrawal_Rate_% | B3: 4
A4: Target_Retirement_Income_Monthly | B4: 6000

Sheet Accounts
A1: Account
A2: Checking
A3: Brokerage
A4: IRA
A5: Savings

Sheet Categories
A1: Type | B1: Category
A2: Income | B2: Salary
A3: Income | B3: Other
A4: Expense | B4: Housing
A5: Expense | B5: Utilities
A6: Expense | B6: Food
A7: Expense | B7: Transportation
A8: Expense | B8: Healthcare
A9: Expense | B9: Investment

Sheet Transactions
A1: Date | B1: Account | C1: Type | D1: Category | E1: Subcategory | F1: Description | G1: Amount
A2: 45803 | B2: Checking | C2: Income | D2: Salary | E2: Paycheck | F2: Monthly paycheck | G2: 6000
A3: 45808 | B3: Checking | C3: Expense | D3: Housing | E3: Rent | F3: May rent | G3: -1800
A4: 45810 | B4: Checking | C4: Expense | D4: Utilities | E4: Electric | F4: TXU bill | G4: -210.45
A5: 45833 | B5: Checking | C5: Income | D5: Salary | E5: Paycheck | F5: Monthly paycheck | G5: 6000
A6: 45838 | B6: Checking | C6: Expense | D6: Housing | E6: Rent | F6: June rent | G6: -1800
A7: 45840 | B7: Checking | C7: Expense | D7: Food | E7: Groceries | F7: Groceries | G7: -285.72
A8: 45848 | B8: Brokerage | C8: Expense | D8: Investment | E8: Buy | F8: Buy FNGU | G8: -3375
A9: 45849 | B9: Brokerage | C9: Expense | D9: Investment | E9: Buy | F9: Buy SPY | G9: -10100
A10: 45863 | B10: Checking | C10: Income | D10: Salary | E10: Paycheck | F10: Monthly paycheck | G10: 6000
A11: 45868 | B11: Checking | C11: Expense | D11: Housing | E11: Rent | F11: July rent | G11: -1800
A12: 45873 | B12: Checking | C12: Expense | D12: Utilities | E12: Electric | F12: TXU bill | G12: -215.19
A13: 45883 | B13: Checking | C13: Income | D13: Other | E13: Refund | F13: Tax refund | G13: 450

Sheet Holdings
A1: Account | B1: Symbol | C1: Quantity | D1: CostBasis | E1: LatestPrice | F1: MarketValue | G1: UnrealizedGain
A2: Brokerage | B2: FNGU | C2: 150 | D2: 3750 | E2: =LOOKUP(2,1/(Prices!$B:$B=Holdings!B2),Prices!$C:$C) | F2: =C2*E2 | G2: =F2-D2
A3: Brokerage | B3: SPY | C3: 20 | D3: 10000 | E3: =LOOKUP(2,1/(Prices!$B:$B=Holdings!B3),Prices!$C:$C) | F3: =C3*E3 | G3: =F3-D3

Sheet Prices
A1: Date | B1: Symbol | C1: Close
A2: 45768 | B2: FNGU | C2: 31.03
A3: 45769 | B3: FNGU | C3: 30.76
A4: 45770 | B4: FNGU | C4: 30.79
A5: 45771 | B5: FNGU | C5: 31.06
A6: 45772 | B6: FNGU | C6: 30.58
A7: 45773 | B7: FNGU | C7: 30.6
A8: 45774 | B8: FNGU | C8: 30.61
A9: 45775 | B9: FNGU | C9: 29.56
A10: 45776 | B10: FNGU | C10: 30.17
A11: 45777 | B11: FNGU | C11: 30.55
A12: 45778 | B12: FNGU | C12: 30.18
A13: 45779 | B13: FNGU | C13: 30.09
... A243: 45888 | B243: SPY | C243: 431.96

Sheet Portfolio_History
A1: Date | B1: FNGU_Value | C1: SPY_Value | D1: TotalValue
A2: 45768 | B2: 4654.5 | C2: 10229.2 | D2: 14883.7
A3: 45769 | B3: 4614 | C3: 10364.8 | D3: 14978.8
A4: 45770 | B4: 4618.5 | C4: 10397 | D4: 15015.5
A5: 45771 | B5: 4659 | C5: 10386.4 | D5: 15045.4
A6: 45772 | B6: 4587 | C6: 10553.8 | D6: 15140.8
A7: 45773 | B7: 4590 | C7: 10662.4 | D7: 15252.4
A8: 45774 | B8: 4591.5 | C8: 10744.8 | D8: 15336.3
A9: 45775 | B9: 4434 | C9: 10957.4 | D9: 15391.4
A10: 45776 | B10: 4525.5 | C10: 11025 | D10: 15550.5
A11: 45777 | B11: 4582.5 | C11: 10894.6 | D11: 15477.1
A12: 45778 | B12: 4527 | C12: 10821 | D12: 15348
A13: 45779 | B13: 4513.5 | C13: 10713.8 | D13: 15227.3
... A122: 45888 | B122: 4987.5 | C122: 8639.2 | D122: 13626.7

Sheet Performance
A1: Symbol | B1: LastPrice | C1: Return_120D_% | D1: Volatility_Ann_% | E1: Max_Drawdown_%
A2: FNGU | B2: 33.25 | C2: 7.15 | D2: 31.42 | E2: -16.32
A3: SPY | B3: 431.96 | C3: -15.54 | D3: 29.34 | E3: -26.18

Sheet Cashflow
A1: YearMonth | B1: Expense | C1: Income | D1: Net
A2: 2025-05 | B2: -1800 | C2: 6000 | D2: 4200
A3: 2025-06 | B3: -2010.45 | C3: 6000 | D3: 3989.55
A4: 2025-07 | B4: -15560.72 | C4: 6000 | D4: -9560.72
A5: 2025-08 | B5: -215.19 | C5: 450 | D5: 234.81

Sheet Summary
A1: Metric | B1: Value
A2: Total Portfolio Value | B2: =SUM(Holdings!F2:F3)
A3: Total Cost Basis | B3: =SUM(Holdings!D2:D3)
A4: Total Unrealized Gain | B4: =SUM(Holdings!G2:G3)
A5: Monthly Income (last full month) | B5: =SUMIF(Cashflow!A:A,B13,Cashflow!B:B)
A6: Monthly Expenses (last full month) | B6: =SUMIF(Cashflow!A:A,B13,Cashflow!C:C)
A7: Net Cashflow (last full month) | B7: =SUMIF(Cashflow!A:A,B13,Cashflow!D:D)
A8: Monthly Expense Baseline (Settings) | B8: =Settings!B2
A9: Safe Withdrawal Rate % (Settings) | B9: =Settings!B3
A10: Target Retirement Income Monthly | B10: =Settings!B4
A11: Required Nest Egg (Baseline/SWR) | B11: =(Settings!B2*12)/(Settings!B3/100)
A12: Funded Ratio (Portfolio / Required) | B12: =B2/B10
A13: Last Full Month (YYYY-MM) | B13: =TEXT(EDATE(TODAY(),-1),yyyy-mm)

Sheet Dashboard
A1: IntelIntent Investment Dashboard
A3: Total Portfolio Value | B3: =Summary!B2
A4: Unrealized Gain | B4: =Summary!B4
A5: Funded Ratio | B5: =Summary!B11
A8: Symbol | B8: MarketValue
A9: =Holdings!B2 | B9: =Holdings!F2
A10: =Holdings!B3 | B10: =Holdings!F3
